{"id":"ff33b00e-0089-42fd-b9ef-7e50b79f2dc0","ingredients":[{"amount":1.0,"name":"filet de poulet"},{"amount":30.0,"name":"panure","unit":"g"},{"amount":10.0,"name":"parmesan","unit":"g"},{"amount":1.0,"name":"oeuf"},{"amount":20.0,"name":"farine","unit":"g"},{"name":"paprika"},{"name":"huile de tournesol"},{"amount":30.0,"name":"beurre a l'ail","unit":"g"}],"name":"Poulet à la Kiev","steps":[{"step":"Ouvrir le filet, mettre le beurre à l'ail dedans."},{"step":"Préchauffer le four à 200°."},{"step":"Paner à l'anglaise."},{"step":"Cuire 2-3 minutes dans de l'huile."},{"step":"Faire cuire au four 20-25 minutes "}]}